dataPreprocessing/__init__.py
dataPreprocessing/categorical_encoder.py
dataPreprocessing/data_type_converter.py
dataPreprocessing/datetime_handler.py
dataPreprocessing/feature_engineer.py
dataPreprocessing/missing_value_handler.py
dataPreprocessing/outlier_handler.py
dataPreprocessing/scaler.py
dataPreprocessing/text_cleaner.py
tests/__init__.py
tests/test_categorical_encoder.py
tests/test_data_type_converter.py
tests/test_datetime_handler.py
tests/test_feature_engineer.py
tests/test_missing_value_handler.py
tests/test_outlier_handler.py
tests/test_scaler.py
tests/test_text_cleaner.py
data_preprocessing_lib_rbb-0.0.1b0.dist-info/METADATA
data_preprocessing_lib_rbb-0.0.1b0.dist-info/WHEEL
data_preprocessing_lib_rbb-0.0.1b0.dist-info/top_level.txt
data_preprocessing_lib_rbb-0.0.1b0.dist-info/RECORD
