Metadata-Version: 2.1
Name: data_preprocessing_lib_rbb
Version: 0.0.1b0
Summary: A data preprocessing library in Python
Home-page: https://github.com/rafetbartug
Author-email: rafetbartug@gmail.com
Classifier: Programming Language :: Python :: 3.12
Classifier: License :: OSI Approved :: MIT License
Classifier: Operating System :: OS Independent
Requires-Python: >=3.6
Requires-Dist: pandas
Requires-Dist: numpy
Requires-Dist: nltk
Requires-Dist: scikit-learn
